ACCOUNT/__init__.py
ACCOUNT/account.py
IAM/__init__.py
Lambda/__init__.py
Lambda/ticket1.py
RDS/__init__.py
RDS/ticket1.py
ROUTE53/__init__.py
ROUTE53/ticket2.py
shared_scripts/__init__.py
shared_scripts/modules.py
aws_farrukh90-0.0.49.dist-info/LICENSE
aws_farrukh90-0.0.49.dist-info/METADATA
aws_farrukh90-0.0.49.dist-info/WHEEL
aws_farrukh90-0.0.49.dist-info/top_level.txt
aws_farrukh90-0.0.49.dist-info/RECORD
